{
  "id": "mock-doc-id",
  "url": null,
  "type": "trigo",
  "href": null,
  "tags": [],
  "first_publication_date": "1970-01-01T00:00:01+0000",
  "last_publication_date": "1970-01-01T00:00:01+0000",
  "slugs": [],
  "linked_documents": [],
  "lang": "en-us",
  "alternate_languages": [],
  "data": {
    "nuevo": false,
    "nombre": "open",
    "imagen": {
      "dimensions": {
        "width": 900,
        "height": 500
      },
      "alt": null,
      "copyright": null,
      "url": "https://images.unsplash.com/photo-1607582278038-6bebbd4d7b72"
    },
    "ciclo": "Largo",
    "imagen_siembra_1": {
      "dimensions": {
        "width": 900,
        "height": 500
      },
      "alt": null,
      "copyright": null,
      "url": "https://images.unsplash.com/photo-1498050108023-c5249f4df085"
    },
    "imagen_siembra_2": {
      "dimensions": {
        "width": 900,
        "height": 500
      },
      "alt": null,
      "copyright": null,
      "url": "https://images.unsplash.com/photo-1544731612-de7f96afe55f"
    },
    "slices": []
  }
}